argo/workflows/sdk/__about__.py
argo/workflows/sdk/__init__.py
argo/workflows/sdk/_arguments.py
argo/workflows/sdk/_base.py
argo/workflows/sdk/_inputs.py
argo/workflows/sdk/_outputs.py
argo/workflows/sdk/_utils.py
argo/workflows/sdk/_workflow.py
argo/workflows/sdk/tasks.py
argo/workflows/sdk/templates.py
argo_workflows_sdk-0.1.0.dev0.dist-info/LICENSE
argo_workflows_sdk-0.1.0.dev0.dist-info/METADATA
argo_workflows_sdk-0.1.0.dev0.dist-info/WHEEL
argo_workflows_sdk-0.1.0.dev0.dist-info/top_level.txt
argo_workflows_sdk-0.1.0.dev0.dist-info/RECORD
