Metadata-Version: 2.1
Name: argo-workflows-sdk
Version: 0.1.0.dev0
Summary: SDK for Argo Workflows
Home-page: https://github.com/CermakM/argo-python-sdk
Author: Marek Cermak
Author-email: macermak@redhat.com
License: Apache Software License
Platform: UNKNOWN
Classifier: Development Status :: 2 - Pre-Alpha
Classifier: Intended Audience :: Developers
Classifier: Intended Audience :: Information Technology
Classifier: License :: OSI Approved :: Apache Software License
Classifier: Operating System :: OS Independent
Classifier: Programming Language :: Python :: 3.6
Classifier: Programming Language :: Python :: 3.7
Classifier: Topic :: Software Development
Classifier: Topic :: Utilities
Requires-Dist: argo-workflows (>=2.1.4)
Requires-Dist: inflection
Requires-Dist: pyyaml
